flask_xcaptcha.py
Flask_xCaptcha-0.5.5.dist-info/LICENSE
Flask_xCaptcha-0.5.5.dist-info/METADATA
Flask_xCaptcha-0.5.5.dist-info/WHEEL
Flask_xCaptcha-0.5.5.dist-info/top_level.txt
Flask_xCaptcha-0.5.5.dist-info/RECORD
