Metadata-Version: 2.1
Name: Flask-xCaptcha
Version: 0.5.5
Summary: The new xCaptcha implementation for Flask without Flask-WTF
Home-page: https://github.com/bmaximuml/flask-xcaptcha
Download-URL: https://github.com/bmaximuml/flask-xcaptcha/tarball/master
Author: Max Levine
Author-email: max@maxlevine.co.uk
License: MIT
Keywords: flask,recaptcha,hcaptcha,xcaptcha,validate
Platform: any
Classifier: Environment :: Web Environment
Classifier: Intended Audience :: Developers
Classifier: License :: OSI Approved :: BSD License
Classifier: Operating System :: OS Independent
Classifier: Programming Language :: Python
Classifier: Programming Language :: Python :: 2
Classifier: Programming Language :: Python :: 2.7
Classifier: Programming Language :: Python :: 3
Classifier: Programming Language :: Python :: 3.4
Classifier: Programming Language :: Python :: 3.5
Classifier: Programming Language :: Python :: 3.6
Classifier: Programming Language :: Python :: 3.7
Classifier: Programming Language :: Python :: 3.8
Classifier: Topic :: Internet :: WWW/HTTP :: Dynamic Content
Classifier: Topic :: Software Development :: Libraries :: Python Modules
License-File: LICENSE
Requires-Dist: flask
Requires-Dist: requests
Requires-Dist: MarkupSafe
